gebaSpike/__init__.py
gebaSpike/__main__.py
gebaSpike/main.py
gebaSpike/core/PopUpCutting.py
gebaSpike/core/Tint_Matlab.py
gebaSpike/core/__init__.py
gebaSpike/core/custom_widgets.py
gebaSpike/core/default_parameters.py
gebaSpike/core/feature_functions.py
gebaSpike/core/feature_plot.py
gebaSpike/core/gui_utils.py
gebaSpike/core/legacyCut.py
gebaSpike/core/plot_functions.py
gebaSpike/core/plot_utils.py
gebaSpike/core/undo.py
gebaSpike/core/waveform_cut_functions.py
gebaSpike/core/writeCut.py
gebaSpike/exporters/Exporter.py
gebaSpike/exporters/ImageExporter.py
gebaSpike/exporters/__init__.py
gebaSpike/exporters/tests/__init__.py
gebaSpike/exporters/tests/test_csv.py
gebaSpike/exporters/tests/test_svg.py
gebaSpike/img/GEBA_Logo.png
gebaSpike/img/__init__.py
gebaSpike-1.1.0.dist-info/LICENSE
gebaSpike-1.1.0.dist-info/METADATA
gebaSpike-1.1.0.dist-info/WHEEL
gebaSpike-1.1.0.dist-info/top_level.txt
gebaSpike-1.1.0.dist-info/RECORD
