Metadata-Version: 2.1
Name: gebaSpike
Version: 1.1.0
Summary: gebaSpike - GUI designed to improve manual spike sorting of in-vivo electrophysiology data.
Home-page: https://github.com/GeoffBarrett/gebaSpike.git
Author: Geoffrey Barrett
Author-email: geoffrey.m.barrett@gmail.com
License: UNKNOWN
Platform: UNKNOWN
Classifier: Programming Language :: Python :: 3.7 
Classifier: License :: OSI Approved :: GNU General Public License v3 (GPLv3) 
Classifier: Operating System :: OS Independent
Requires-Dist: PyQtGraph
Requires-Dist: PyQt5
Requires-Dist: matplotlib
Requires-Dist: numpy
Requires-Dist: scipy
Requires-Dist: PyOpenGl
Requires-Dist: sklearn
